cloudtracker/__init__.py
cloudtracker/cli.py
cloudtracker/data/aws_api_list.txt
cloudtracker/data/cloudtrail_supported_actions.txt
cloudtracker/datasources/__init__.py
cloudtracker/datasources/athena.py
cloudtracker/datasources/es.py
cloudtracker-2.1.5.dist-info/LICENSE
cloudtracker-2.1.5.dist-info/METADATA
cloudtracker-2.1.5.dist-info/WHEEL
cloudtracker-2.1.5.dist-info/entry_points.txt
cloudtracker-2.1.5.dist-info/top_level.txt
cloudtracker-2.1.5.dist-info/zip-safe
cloudtracker-2.1.5.dist-info/RECORD
