Metadata-Version: 2.1
Name: cloudtracker
Version: 2.1.5
Summary: CloudTracker helps you find over-privileged IAM users and roles by comparing CloudTrail logs with current IAM policies
Home-page: https://github.com/duo-labs/cloudtracker
Author: Duo Security
License: BSD 3
Keywords: aws cloudtracker cloudtrail privileged iam user roles policy policies
Platform: UNKNOWN
Classifier: License :: OSI Approved :: BSD License
Classifier: Programming Language :: Python :: 3
Classifier: Programming Language :: Python :: 3.3
Classifier: Programming Language :: Python :: 3.4
Classifier: Programming Language :: Python :: 3.5
Classifier: Programming Language :: Python :: 3.6
Classifier: Programming Language :: Python :: 3.7
Classifier: Programming Language :: Python :: 3 :: Only
Classifier: Development Status :: 5 - Production/Stable
Requires-Dist: ansicolors (==1.1.8)
Requires-Dist: boto3 (==1.5.32)
Requires-Dist: jmespath (==0.9.3)
Requires-Dist: pyyaml (==4.2b4)
Provides-Extra: dev
Requires-Dist: coverage ; extra == 'dev'
Requires-Dist: nose ; extra == 'dev'
Requires-Dist: autoflake ; extra == 'dev'
Requires-Dist: autopep8 ; extra == 'dev'
Requires-Dist: pylint ; extra == 'dev'
Provides-Extra: es1
Requires-Dist: elasticsearch (==1.9.0) ; extra == 'es1'
Requires-Dist: elasticsearch-dsl (==0.0.11) ; extra == 'es1'
Provides-Extra: es6
Requires-Dist: elasticsearch (==6.1.1) ; extra == 'es6'
Requires-Dist: elasticsearch-dsl (==6.1.0) ; extra == 'es6'
